collective.catalogcleanup-2.0.0-py3.11-nspkg.pth
collective/catalogcleanup/__init__.py
collective/catalogcleanup/browser.py
collective/catalogcleanup/configure.zcml
collective/catalogcleanup/testing.py
collective/catalogcleanup/tests/__init__.py
collective/catalogcleanup/tests/test_functional.py
collective.catalogcleanup-2.0.0.dist-info/METADATA
collective.catalogcleanup-2.0.0.dist-info/WHEEL
collective.catalogcleanup-2.0.0.dist-info/entry_points.txt
collective.catalogcleanup-2.0.0.dist-info/namespace_packages.txt
collective.catalogcleanup-2.0.0.dist-info/top_level.txt
collective.catalogcleanup-2.0.0.dist-info/RECORD
