Metadata-Version: 2.1
Name: collective.catalogcleanup
Version: 2.0.0
Summary: Remove outdated items from the catalog
Home-page: https://github.com/collective/collective.catalogcleanup
Author: Maurits van Rees
Author-email: m.van.rees@zestsoftware.nl
License: GPL
Keywords: plone catalog cleanup
Classifier: Development Status :: 5 - Production/Stable
Classifier: Framework :: Plone
Classifier: Framework :: Plone :: 5.2
Classifier: Framework :: Plone :: 6.0
Classifier: Programming Language :: Python
Classifier: Programming Language :: Python :: 3.8
Classifier: Programming Language :: Python :: 3.9
Classifier: Programming Language :: Python :: 3.10
Classifier: Programming Language :: Python :: 3.11
Classifier: License :: OSI Approved :: GNU General Public License (GPL)
Requires-Python: >=3.8
Requires-Dist: plone.protect
Requires-Dist: plone.uuid
Requires-Dist: Products.CMFCore
Requires-Dist: Products.CMFPlone
Requires-Dist: setuptools
Provides-Extra: test
Requires-Dist: collective.noindexing ; extra == 'test'
Requires-Dist: plone.app.testing ; extra == 'test'
